MANIFEST.in
README.rst
setup.py
geocell/__init__.py
geocell/geocell.py
geocell.egg-info/PKG-INFO
geocell.egg-info/SOURCES.txt
geocell.egg-info/dependency_links.txt
geocell.egg-info/requires.txt
geocell.egg-info/top_level.txt
geocell/template/google_cellmap_template.html