Metadata-Version: 1.1
Name: geocell
Version: 0.9.0
Summary: Location estimation using GSM Cells with Google Maps Geolocation API
Home-page: http://github.com/kmertol/geocell
Author: Kaan Mertol
Author-email: kmertol@gmail.com
License: MIT
Keywords: geolocation location cell
Platform: UNKNOWN
Classifier: Programming Language :: Python :: 3
Classifier: Development Status :: 4 - Beta
Classifier: Topic :: Utilities
Classifier: License :: OSI Approved :: MIT License
Classifier: Operating System :: OS Independent
